greetron/__init__.py
greetron/cli.py
greetron/greetings.py
greetron-0.1.3.dist-info/METADATA
greetron-0.1.3.dist-info/WHEEL
greetron-0.1.3.dist-info/entry_points.txt
greetron-0.1.3.dist-info/top_level.txt
greetron-0.1.3.dist-info/RECORD
