Metadata-Version: 2.4
Name: greetron
Version: 0.1.3
Summary: A lightweight library to generate formal and informal greetings and goodbyes.
Author-email: Aryan Bhan <vsaryan151@gmail.com>
License: MIT
Project-URL: Homepage, https://pypi.org/project/greetron
Keywords: greeting,chatbot,assistant,conversation,friendly-bot
Classifier: Development Status :: 3 - Alpha
Classifier: Intended Audience :: Developers
Classifier: Topic :: Communications :: Chat
Classifier: License :: OSI Approved :: MIT License
Classifier: Programming Language :: Python :: 3
Classifier: Programming Language :: Python :: 3.7
Classifier: Programming Language :: Python :: 3.8
Classifier: Programming Language :: Python :: 3.9
Classifier: Programming Language :: Python :: 3.10
Classifier: Programming Language :: Python :: 3.11
Requires-Python: >=3.7
